ttsmms/__init__.py
ttsmms/attentions.py
ttsmms/commons.py
ttsmms/data_utils.py
ttsmms/losses.py
ttsmms/mel_processing.py
ttsmms/models.py
ttsmms/modules.py
ttsmms/preprocess.py
ttsmms/transforms.py
ttsmms/utils.py
ttsmms/text/__init__.py
ttsmms/text/cleaners.py
ttsmms/text/symbols.py
py3_ttsmms-0.8.25.dist-info/LICENSE
py3_ttsmms-0.8.25.dist-info/METADATA
py3_ttsmms-0.8.25.dist-info/WHEEL
py3_ttsmms-0.8.25.dist-info/top_level.txt
py3_ttsmms-0.8.25.dist-info/RECORD
