Metadata-Version: 2.1
Name: py3-ttsmms
Version: 0.8.25
Summary: Text-to-speech with The Massively Multilingual Speech (MMS) project
Home-page: https://github.com/willwade/ttsmms
Author: willwade
Author-email: willwade <willwade@gmail.com>
License: MIT License
Project-URL: Homepage, https://github.com/willwade/ttsmms
Project-URL: Repository, https://github.com/willwade/ttsmms
Classifier: Programming Language :: Python :: 3
Classifier: Programming Language :: Python :: 3.10
Classifier: Programming Language :: Python :: 3.11
Classifier: Programming Language :: Python :: 3.12
Requires-Python: >=3.6
License-File: LICENSE
Requires-Dist: Cython ==0.29.30
Requires-Dist: librosa ==0.10.0
Requires-Dist: scipy ==1.14.0
Requires-Dist: numpy ==1.24.3
Requires-Dist: phonemizer >=3.2.1
Requires-Dist: torch >=2.3.1
Requires-Dist: Unidecode >=1.3.7
Requires-Dist: monotonic-align >=1.0.0
